cacts/__init__.py
cacts/build_type.py
cacts/cacts.py
cacts/get_mach_env.py
cacts/machine.py
cacts/parse_config.py
cacts/project.py
cacts/utils.py
cacts/version.py
cacts/tests/test_build_type.py
cacts/tests/test_cacts.py
cacts/tests/test_deploy.sh
cacts/tests/test_machine.py
cacts/tests/test_project.py
cacts/tests/test_utils.py
cacts-0.2.4.dist-info/METADATA
cacts-0.2.4.dist-info/WHEEL
cacts-0.2.4.dist-info/entry_points.txt
cacts-0.2.4.dist-info/RECORD
