Metadata-Version: 2.4
Name: cacts
Version: 0.2.4
Summary: A framework for configurable unit testing of a cmake-based project
Author-email: Luca Bertagna <lbertag@sandia.gov>, James Foucar <jgfouca@sandia.gov>, Naser Mahfouz <naser.mahfouz@pnnl.gov>
Maintainer-email: Luca Bertagna <lbertag@sandia.gov>, James Foucar <jgfouca@sandia.gov>, Naser Mahfouz <naser.mahfouz@pnnl.gov>
Requires-Python: >=3.6
Requires-Dist: psutil
Requires-Dist: pyyaml
